{
  "id": "zone_01",
  "spawn": [200, 580],
  "platforms": [
    {"x": 0,    "y": 660, "w": 10000, "h": 60, "label": "ground"},
    {"x": 300,  "y": 540, "w": 200,   "h": 20},
    {"x": 600,  "y": 460, "w": 180,   "h": 20},
    {"x": 900,  "y": 380, "w": 160,   "h": 20},
    {"x": 1200, "y": 460, "w": 200,   "h": 20},
    {"x": 1500, "y": 540, "w": 250,   "h": 20}
  ],
  "enemies": [
    {"type": "basic", "x": 500,  "y": 600},
    {"type": "basic", "x": 800,  "y": 600},
    {"type": "basic", "x": 1100, "y": 600}
  ],
  "save_points": [
    {"x": 50, "y": 596, "w": 60, "h": 64}
  ]
}
